odoo/addons/stock_move_forced_lot/README.rst
odoo/addons/stock_move_forced_lot/__init__.py
odoo/addons/stock_move_forced_lot/__manifest__.py
odoo/addons/stock_move_forced_lot/i18n/es.po
odoo/addons/stock_move_forced_lot/i18n/it.po
odoo/addons/stock_move_forced_lot/i18n/stock_move_forced_lot.pot
odoo/addons/stock_move_forced_lot/models/__init__.py
odoo/addons/stock_move_forced_lot/models/stock_move.py
odoo/addons/stock_move_forced_lot/models/stock_rule.py
odoo/addons/stock_move_forced_lot/readme/CONTRIBUTORS.rst
odoo/addons/stock_move_forced_lot/readme/DESCRIPTION.rst
odoo/addons/stock_move_forced_lot/static/description/icon.png
odoo/addons/stock_move_forced_lot/static/description/index.html
odoo/addons/stock_move_forced_lot/tests/__init__.py
odoo/addons/stock_move_forced_lot/tests/test_stock_move_forced_lot.py
odoo14_addon_stock_move_forced_lot-14.0.1.0.1.dev8.dist-info/METADATA
odoo14_addon_stock_move_forced_lot-14.0.1.0.1.dev8.dist-info/WHEEL
odoo14_addon_stock_move_forced_lot-14.0.1.0.1.dev8.dist-info/top_level.txt
odoo14_addon_stock_move_forced_lot-14.0.1.0.1.dev8.dist-info/RECORD
