Metadata-Version: 2.1
Name: odoo14-addon-stock-move-forced-lot
Version: 14.0.1.0.1.dev8
Summary: This module allows you to set a lot_id in a procurement to force the stock move generated to only reserve the selected lot.
Home-page: https://github.com/OCA/stock-logistics-workflow
Author: ForgeFlow, Odoo Community Association (OCA)
Author-email: support@odoo-community.org
License: LGPL-3
Platform: UNKNOWN
Classifier: Programming Language :: Python
Classifier: Framework :: Odoo
Classifier: Framework :: Odoo :: 14.0
Classifier: License :: OSI Approved :: GNU Lesser General Public License v3 (LGPLv3)
Requires-Python: >=3.6
Requires-Dist: odoo <14.1dev,>=14.0a
